{
  "result": {
    "id": "crockpot:monster_lasagna",
    "Count": 1
  },
  "requirements": [
    {
      "type": "must_contain_ingredient",
      "ingredient": {
        "item": "minecraft:rotten_flesh"
      },
      "quantity": 1
    },
	{
		"type": "combination_or",
		"first":{
		  "type": "category_min_exclusive",
		  "category": "INEDIBLE",
		  "min": 0.0
		},
		"second":{
		  "type": "category_min_exclusive",
		  "category": "FROZEN",
		  "min": 0.0
		}
	}
  ],
  "cookTime": 400,
  "weight": 1,
  "priority": 16,
  "potLevel": 0
}